odoo/addons/stock_lot_scrap/README.rst
odoo/addons/stock_lot_scrap/__init__.py
odoo/addons/stock_lot_scrap/__manifest__.py
odoo/addons/stock_lot_scrap/i18n/de.po
odoo/addons/stock_lot_scrap/i18n/es.po
odoo/addons/stock_lot_scrap/i18n/fr.po
odoo/addons/stock_lot_scrap/i18n/hr.po
odoo/addons/stock_lot_scrap/i18n/it.po
odoo/addons/stock_lot_scrap/i18n/pt.po
odoo/addons/stock_lot_scrap/i18n/pt_BR.po
odoo/addons/stock_lot_scrap/i18n/sl.po
odoo/addons/stock_lot_scrap/i18n/stock_lot_scrap.pot
odoo/addons/stock_lot_scrap/models/__init__.py
odoo/addons/stock_lot_scrap/models/stock_lot.py
odoo/addons/stock_lot_scrap/models/stock_scrap.py
odoo/addons/stock_lot_scrap/readme/CONFIGURE.md
odoo/addons/stock_lot_scrap/readme/CONTRIBUTORS.md
odoo/addons/stock_lot_scrap/readme/DESCRIPTION.md
odoo/addons/stock_lot_scrap/readme/USAGE.md
odoo/addons/stock_lot_scrap/static/description/icon.png
odoo/addons/stock_lot_scrap/static/description/index.html
odoo/addons/stock_lot_scrap/tests/__init__.py
odoo/addons/stock_lot_scrap/tests/test_stock_lot_scrap.py
odoo_addon_stock_lot_scrap-18.0.1.0.1.1.dist-info/METADATA
odoo_addon_stock_lot_scrap-18.0.1.0.1.1.dist-info/WHEEL
odoo_addon_stock_lot_scrap-18.0.1.0.1.1.dist-info/top_level.txt
odoo_addon_stock_lot_scrap-18.0.1.0.1.1.dist-info/RECORD
