Metadata-Version: 2.1
Name: odoo-addon-stock_lot_scrap
Version: 18.0.1.0.1.1
Requires-Python: >=3.10
Requires-Dist: odoo==18.0.*
Summary: This module adds a button in Production Lot/Serial Number view form to Scrap all products contained.
Home-page: https://github.com/OCA/stock-logistics-workflow
License: AGPL-3
Author: Tecnativa,Odoo Community Association (OCA)
Author-email: support@odoo-community.org
Classifier: Programming Language :: Python
Classifier: Framework :: Odoo
Classifier: Framework :: Odoo :: 18.0
Classifier: License :: OSI Approved :: GNU Affero General Public License v3
